superb_logger-0.2.4.dist-info/METADATA
superb_logger-0.2.4.dist-info/WHEEL
superb_logger-0.2.4.dist-info/entry_points.txt
superb_logger/__init__.py
superb_logger/configurator.py
superb_logger/constants.py
superb_logger/enums.py
superb_logger-0.2.4.dist-info/RECORD
