Metadata-Version: 2.1
Name: superb_logger
Version: 0.2.4
Summary: Superb Logger is a sleek and powerful logging utility built for Python applications
Author-Email: dkurchigin <kurchigin.dmitry@yandex.ru>
License: MIT
Classifier: Programming Language :: Python :: 3
Classifier: Programming Language :: Python
Classifier: Typing :: Typed
Classifier: Programming Language :: Python :: 3 :: Only
Classifier: Programming Language :: Python :: 3.10
Classifier: Programming Language :: Python :: 3.11
Classifier: Programming Language :: Python :: 3.12
Classifier: Programming Language :: Python :: 3.13
Project-URL: Homepage, https://gitverse.ru/dkurchigin/superb_logger
Project-URL: Documentation, https://superb-logger.dkurchigin.ru/
Project-URL: Source, https://gitverse.ru/dkurchigin/superb_logger
Requires-Python: >=3.10
Requires-Dist: pydantic>=2.11.7
